discord/ext/ipc/__init__.py
discord/ext/ipc/client.py
discord/ext/ipc/errors.py
discord/ext/ipc/server.py
discord.py_ipc-1.1.0.dist-info/LICENSE
discord.py_ipc-1.1.0.dist-info/METADATA
discord.py_ipc-1.1.0.dist-info/WHEEL
discord.py_ipc-1.1.0.dist-info/top_level.txt
discord.py_ipc-1.1.0.dist-info/RECORD
