Metadata-Version: 2.1
Name: discord.py-ipc
Version: 1.1.0
Summary: A discord.py extension for inter-process communication.
Home-page: https://github.com/Sn1F3rt/discord.py-ipc
Author: Sn1F3rt
License: Apache Software License
Project-URL: Documentation, https://discordpy-ipc.readthedocs.io/en/latest/
Project-URL: Issue Tracker, https://github.com/Sn1F3rt/discord.py-ipc/issues
Classifier: Development Status :: 4 - Beta
Classifier: Framework :: AsyncIO
Classifier: License :: OSI Approved :: Apache Software License
Classifier: Intended Audience :: Developers
Classifier: Natural Language :: English
Classifier: Operating System :: OS Independent
Classifier: Programming Language :: Python :: 3.8
Classifier: Programming Language :: Python :: 3.9
Classifier: Topic :: Internet
Classifier: Topic :: Software Development :: Libraries
Classifier: Topic :: Software Development :: Libraries :: Python Modules
Classifier: Topic :: Utilities
Classifier: Typing :: Typed
Requires-Python: >=3.8.0
License-File: LICENSE
Requires-Dist: discord.py
Provides-Extra: docs
Requires-Dist: sphinx ; extra == 'docs'
Requires-Dist: sphinxcontrib-trio ; extra == 'docs'
Requires-Dist: sphinx-rtd-theme ; extra == 'docs'
